{
  "hash": "bf242370",
  "browserHash": "305fac97",
  "optimized": {
    "vue": {
      "src": "../../../../node_modules/vue/dist/vue.runtime.esm-bundler.js",
      "file": "vue.js",
      "fileHash": "e498e666",
      "needsInterop": false
    },
    "vitepress > @vue/devtools-api": {
      "src": "../../../../node_modules/@vue/devtools-api/lib/esm/index.js",
      "file": "vitepress___@vue_devtools-api.js",
      "fileHash": "3a7d5030",
      "needsInterop": false
    },
    "@theme/index": {
      "src": "../../../../node_modules/vitepress/dist/client/theme-default/index.js",
      "file": "@theme_index.js",
      "fileHash": "d862cec8",
      "needsInterop": false
    }
  },
  "chunks": {
    "chunk-V7AUFIRV": {
      "file": "chunk-V7AUFIRV.js"
    }
  }
}